spapp/__init__.py
spapp/api.py
spapp/exception.py
spapp/node_env.py
spapp/node_params.py
spapp-0.0.2.dist-info/METADATA
spapp-0.0.2.dist-info/WHEEL
spapp-0.0.2.dist-info/top_level.txt
spapp-0.0.2.dist-info/RECORD
