Metadata-Version: 2.1
Name: spapp
Version: 0.0.2
Summary: get node information for suanpan microservice
Home-page: https://gitlab-sp.xuelangyun.com/mocheng.lgy/suanpan-app
Author: mocheng.lgy
Author-email: mocheng.lgy@xuelangyun.com
Project-URL: Source Code, https://gitlab-sp.xuelangyun.com/mocheng.lgy/suanpan-app/
Keywords: suanpan,app,microservice
Requires-Python: >=3.7
Requires-Dist: requests (>=2.28.1)
Requires-Dist: python-dotenv (>=0.20.0)
